[{"path":"./main/数学/漫谈直线/漫谈直线之向量.md","folder":"./main/数学/漫谈直线","name":"漫谈直线之向量.md","type":"md","ossName":"15985276886488506752978097667.md","mtime":1599037929063,"ctime":1598522416546},{"path":"./main/数学/漫谈直线/漫谈直线之点斜式和一般式.md","folder":"./main/数学/漫谈直线","name":"漫谈直线之点斜式和一般式.md","type":"md","ossName":"15979954203825675131427161848.md","mtime":1597995300392,"ctime":1597995300392},{"path":"./main/canvas/绘图方向/绘图方向.md","folder":"./main/canvas/绘图方向","name":"绘图方向.md","type":"md","ossName":"15974705671359128256703121109.md","mtime":1598012741484,"ctime":1597462409269},{"path":"./main/node/自建博客环境/自建博客.md","folder":"./main/node/自建博客环境","name":"自建博客.md","type":"md","ossName":"15969742999736196242075806075.md","mtime":1599188685602,"ctime":1596963699196},{"path":"./main/canvas/图形选择/图形选择-多边形网格化.md","folder":"./main/canvas/图形选择","name":"图形选择-多边形网格化.md","type":"md","ossName":"159694748907505237682342996064.md","mtime":1598345698000,"ctime":1596810559786},{"path":"./main/canvas/图形选择/图形选择-网格选择.md","folder":"./main/canvas/图形选择","name":"图形选择-网格选择.md","type":"md","ossName":"15969474890753088470146588467.md","mtime":1598345698000,"ctime":1596809934699},{"path":"./main/canvas/图形选择/图形选择-物质不易.md","folder":"./main/canvas/图形选择","name":"图形选择-物质不易.md","type":"md","ossName":"15969474890757961242471182095.md","mtime":1598345698000,"ctime":1596809501193},{"path":"./main/canvas/图形选择/图形选择-图形模块化.md","folder":"./main/canvas/图形选择","name":"图形选择-图形模块化.md","type":"md","ossName":"15969474890759875538729278808.md","mtime":1598345698000,"ctime":1596809292054},{"path":"./main/canvas/图形选择/图形选择-isPointInPath(x,y).md","folder":"./main/canvas/图形选择","name":"图形选择-isPointInPath(x,y).md","type":"md","ossName":"15969474890759963491611978199.md","mtime":1598345698000,"ctime":1596807288032},{"path":"./main/canvas/图形选择/图形选择-svg.md","folder":"./main/canvas/图形选择","name":"图形选择-svg.md","type":"md","ossName":"15969474890753217931799094753.md","mtime":1598345698000,"ctime":1596807288031}]